LICENSE
MANIFEST.in
README.rst
setup.cfg
setup.py
snakebacon/__init__.py
snakebacon/agedepth.py
snakebacon/mcmc.py
snakebacon/records.py
snakebacon/utils.py
snakebacon/version.py
snakebacon.egg-info/PKG-INFO
snakebacon.egg-info/SOURCES.txt
snakebacon.egg-info/dependency_links.txt
snakebacon.egg-info/requires.txt
snakebacon.egg-info/top_level.txt
snakebacon/mcmcbackends/__init__.py
snakebacon/mcmcbackends/bacon/Matrix.cpp
snakebacon/mcmcbackends/bacon/Matrix.h
snakebacon/mcmcbackends/bacon/__init__.py
snakebacon/mcmcbackends/bacon/bacon.cpp
snakebacon/mcmcbackends/bacon/bacon.h
snakebacon/mcmcbackends/bacon/bacon.pxd
snakebacon/mcmcbackends/bacon/baconwrap.cpp
snakebacon/mcmcbackends/bacon/baconwrap.pyx
snakebacon/mcmcbackends/bacon/cal.h
snakebacon/mcmcbackends/bacon/calibcurves.py
snakebacon/mcmcbackends/bacon/input.cpp
snakebacon/mcmcbackends/bacon/input.h
snakebacon/mcmcbackends/bacon/kernel.cpp
snakebacon/mcmcbackends/bacon/ranfun.cpp
snakebacon/mcmcbackends/bacon/ranfun.h
snakebacon/mcmcbackends/bacon/twalk.h
snakebacon/mcmcbackends/bacon/utils.py
snakebacon/mcmcbackends/bacon/vector.cpp
snakebacon/mcmcbackends/bacon/Curves/3Col_intcal13.14C
snakebacon/mcmcbackends/bacon/Curves/3Col_marine13.14C
snakebacon/mcmcbackends/bacon/Curves/3Col_shcal13.14C
snakebacon/mcmcbackends/bacon/Curves/__init__.py
snakebacon/mcmcbackends/bacon/Curves/intcal13.14C
snakebacon/mcmcbackends/bacon/Curves/marine13.14C
snakebacon/mcmcbackends/bacon/Curves/mixed.14C
snakebacon/mcmcbackends/bacon/Curves/postbomb_NH1.14C
snakebacon/mcmcbackends/bacon/Curves/postbomb_NH2.14C
snakebacon/mcmcbackends/bacon/Curves/postbomb_NH3.14C
snakebacon/mcmcbackends/bacon/Curves/postbomb_SH1-2.14C
snakebacon/mcmcbackends/bacon/Curves/postbomb_SH3.14C
snakebacon/mcmcbackends/bacon/Curves/shcal13.14C
snakebacon/tests/MSB2K.csv
snakebacon/tests/__init__.py
snakebacon/tests/test_agedepth.py
snakebacon/tests/test_bacon_utils.py
snakebacon/tests/test_baconwrap.py
snakebacon/tests/test_chronrecord.py
snakebacon/tests/test_datedproxyrecord.py
snakebacon/tests/test_mcmc.py
snakebacon/tests/test_mcmcbackend_bacon.py
snakebacon/tests/test_utils.py