Metadata-Version: 1.1
Name: snakebacon
Version: 0.0.6
Summary: snakebacon
Home-page: https://github.com/brews/snakebacon
Author: S. Brewster Malevich
Author-email: malevich@email.arizona.edu
License: GPLv3
Keywords: marine radiocarbon c14
Platform: UNKNOWN
Classifier: Development Status :: 3 - Alpha
Classifier: Operating System :: POSIX
Classifier: Intended Audience :: Developers
Classifier: Intended Audience :: Science/Research
Classifier: Topic :: Scientific/Engineering
Classifier: Topic :: Software Development
Classifier: License :: OSI Approved :: GNU General Public License v3 or later (GPLv3+)
Classifier: Programming Language :: Python :: 3
